baserun/__init__.py
baserun/api.py
baserun/mixins.py
baserun/py.typed
baserun/pytest_plugin.py
baserun/utils.py
baserun/worker.py
baserun/integrations/integration.py
baserun/integrations/langchain.py
baserun/integrations/llamaindex.py
baserun/models/__init__.py
baserun/models/dataset.py
baserun/models/evals.py
baserun/models/evaluators.py
baserun/models/experiment.py
baserun/models/scenario.py
baserun/models/tags.py
baserun/wrappers/__init__.py
baserun/wrappers/anthropic.py
baserun/wrappers/generic.py
baserun/wrappers/openai.py
baserun-2.0.9.dist-info/LICENSE
baserun-2.0.9.dist-info/METADATA
baserun-2.0.9.dist-info/WHEEL
baserun-2.0.9.dist-info/entry_points.txt
baserun-2.0.9.dist-info/top_level.txt
baserun-2.0.9.dist-info/RECORD
