Metadata-Version: 2.1
Name: baserun
Version: 2.0.9
Summary: tools for testing, debugging, and evaluating llm features.
Author-email: Erik Peterson <erik@baserun.ai>
License: MIT License
Project-URL: Homepage, https://baserun.ai
Project-URL: Repository, https://github.com/baserun-ai/baserun-py
Requires-Python: >=3.8
License-File: LICENSE
Requires-Dist: httpx[http2] >=0.24.0
Requires-Dist: datasets >=2.0.0
Requires-Dist: pydantic <3,>=2.0.0
Requires-Dist: tenacity >=8.0.1
